fvidal_packages/__init__.py
fvidal_packages/db_api_client/__init__.py
fvidal_packages/db_api_client/parent_cli.py
fvidal_packages/db_api_client/postgres_cli.py
fvidal_packages/db_api_client/sqlite_cli.py
fvidal_packages/stock_utils/__init__.py
fvidal_packages/stock_utils/stock_utils.py
itba_cde_tpf_python_applications_fvidal90-1.5.1.dist-info/WHEEL
itba_cde_tpf_python_applications_fvidal90-1.5.1.dist-info/METADATA
itba_cde_tpf_python_applications_fvidal90-1.5.1.dist-info/RECORD
