Metadata-Version: 2.1
Name: itba-cde-tpf-python-applications-fvidal90
Version: 1.5.1
Summary: TP Vidal
Author: Fernando Vidal
Author-email: picovidal22@gmail.com
Requires-Python: >=3.9,<4.0
Classifier: Programming Language :: Python :: 3
Classifier: Programming Language :: Python :: 3.10
Classifier: Programming Language :: Python :: 3.9
Requires-Dist: SQLAlchemy (==1.4.27)
Requires-Dist: kaleido (==0.2.1)
Requires-Dist: pandas (==1.3.4)
Requires-Dist: plotly (>=5.4.0,<6.0.0)
Requires-Dist: psycopg2-binary (==2.9.2)
Requires-Dist: requests (==2.26.0)
